tg_etl_lib/__init__.py
tg_etl_lib/tg_elt_lib.py
myetljob_run-0.1.0.dist-info/METADATA
myetljob_run-0.1.0.dist-info/WHEEL
myetljob_run-0.1.0.dist-info/top_level.txt
myetljob_run-0.1.0.dist-info/RECORD
